campaign_local/CampaignLocal.py
campaign_local/__init__.py
campaign_local-0.0.3.dist-info/METADATA
campaign_local-0.0.3.dist-info/WHEEL
campaign_local-0.0.3.dist-info/top_level.txt
campaign_local-0.0.3.dist-info/RECORD
