Metadata-Version: 2.1
Name: campaign-local
Version: 0.0.3
Summary: PyPI Package for Circles campaign-local Python
Home-page: https://github.com/circles-zone/campaign-local-python-package
Author: Circles
Author-email: info@circlez.ai
Classifier: Programming Language :: Python :: 3
Classifier: License :: Other/Proprietary License
Classifier: Operating System :: OS Independent
Requires-Dist: logger-local
Requires-Dist: database-mysql-local
